{
  "openapi": "3.0.1",
  "info": {
    "title": "API_ovni",
    "version": "1.0"
  },
  "paths": {
    "/api/OvniData": {
      "get": {
        "tags": [
          "OvniData"
        ],
        "responses": {
          "200": {
            "description": "OK",
            "content": {
              "text/plain": {
                "schema": {
                  "type": "array",
                  "items": {
                    "$ref": "#/components/schemas/OvniData"
                  }
                }
              },
              "application/json": {
                "schema": {
                  "type": "array",
                  "items": {
                    "$ref": "#/components/schemas/OvniData"
                  }
                }
              },
              "text/json": {
                "schema": {
                  "type": "array",
                  "items": {
                    "$ref": "#/components/schemas/OvniData"
                  }
                }
              }
            }
          }
        }
      },
      "post": {
        "tags": [
          "OvniData"
        ],
        "requestBody": {
          "content": {
            "application/json": {
              "schema": {
                "$ref": "#/components/schemas/OvniData"
              }
            },
            "text/json": {
              "schema": {
                "$ref": "#/components/schemas/OvniData"
              }
            },
            "application/*+json": {
              "schema": {
                "$ref": "#/components/schemas/OvniData"
              }
            }
          }
        },
        "responses": {
          "200": {
            "description": "OK"
          }
        }
      }
    },
    "/api/OvniData/{id}": {
      "get": {
        "tags": [
          "OvniData"
        ],
        "parameters": [
          {
            "name": "id",
            "in": "path",
            "required": true,
            "schema": {
              "maxLength": 24,
              "minLength": 24,
              "type": "string"
            }
          }
        ],
        "responses": {
          "200": {
            "description": "OK",
            "content": {
              "text/plain": {
                "schema": {
                  "$ref": "#/components/schemas/OvniData"
                }
              },
              "application/json": {
                "schema": {
                  "$ref": "#/components/schemas/OvniData"
                }
              },
              "text/json": {
                "schema": {
                  "$ref": "#/components/schemas/OvniData"
                }
              }
            }
          }
        }
      },
      "put": {
        "tags": [
          "OvniData"
        ],
        "parameters": [
          {
            "name": "id",
            "in": "path",
            "required": true,
            "schema": {
              "maxLength": 24,
              "minLength": 24,
              "type": "string"
            }
          }
        ],
        "requestBody": {
          "content": {
            "application/json": {
              "schema": {
                "$ref": "#/components/schemas/OvniData"
              }
            },
            "text/json": {
              "schema": {
                "$ref": "#/components/schemas/OvniData"
              }
            },
            "application/*+json": {
              "schema": {
                "$ref": "#/components/schemas/OvniData"
              }
            }
          }
        },
        "responses": {
          "200": {
            "description": "OK"
          }
        }
      },
      "delete": {
        "tags": [
          "OvniData"
        ],
        "parameters": [
          {
            "name": "id",
            "in": "path",
            "required": true,
            "schema": {
              "maxLength": 24,
              "minLength": 24,
              "type": "string"
            }
          }
        ],
        "responses": {
          "200": {
            "description": "OK"
          }
        }
      }
    },
    "/api/OvniData/Data": {
      "get": {
        "tags": [
          "OvniData"
        ],
        "parameters": [
          {
            "name": "dataInicio",
            "in": "query",
            "schema": {
              "type": "string"
            }
          },
          {
            "name": "dataFim",
            "in": "query",
            "schema": {
              "type": "string"
            }
          }
        ],
        "responses": {
          "200": {
            "description": "OK",
            "content": {
              "text/plain": {
                "schema": {
                  "type": "array",
                  "items": {
                    "$ref": "#/components/schemas/OvniData"
                  }
                }
              },
              "application/json": {
                "schema": {
                  "type": "array",
                  "items": {
                    "$ref": "#/components/schemas/OvniData"
                  }
                }
              },
              "text/json": {
                "schema": {
                  "type": "array",
                  "items": {
                    "$ref": "#/components/schemas/OvniData"
                  }
                }
              }
            }
          }
        }
      }
    },
    "/api/OvniData/Companhia Aerea": {
      "get": {
        "tags": [
          "OvniData"
        ],
        "parameters": [
          {
            "name": "companhia",
            "in": "query",
            "schema": {
              "type": "string"
            }
          }
        ],
        "responses": {
          "200": {
            "description": "OK",
            "content": {
              "text/plain": {
                "schema": {
                  "type": "array",
                  "items": {
                    "$ref": "#/components/schemas/OvniData"
                  }
                }
              },
              "application/json": {
                "schema": {
                  "type": "array",
                  "items": {
                    "$ref": "#/components/schemas/OvniData"
                  }
                }
              },
              "text/json": {
                "schema": {
                  "type": "array",
                  "items": {
                    "$ref": "#/components/schemas/OvniData"
                  }
                }
              }
            }
          }
        }
      }
    },
    "/api/OvniData/Origem": {
      "get": {
        "tags": [
          "OvniData"
        ],
        "parameters": [
          {
            "name": "origem",
            "in": "query",
            "schema": {
              "type": "string"
            }
          }
        ],
        "responses": {
          "200": {
            "description": "OK",
            "content": {
              "text/plain": {
                "schema": {
                  "type": "array",
                  "items": {
                    "$ref": "#/components/schemas/OvniData"
                  }
                }
              },
              "application/json": {
                "schema": {
                  "type": "array",
                  "items": {
                    "$ref": "#/components/schemas/OvniData"
                  }
                }
              },
              "text/json": {
                "schema": {
                  "type": "array",
                  "items": {
                    "$ref": "#/components/schemas/OvniData"
                  }
                }
              }
            }
          }
        }
      }
    },
    "/api/OvniData/Destino": {
      "get": {
        "tags": [
          "OvniData"
        ],
        "parameters": [
          {
            "name": "destino",
            "in": "query",
            "schema": {
              "type": "string"
            }
          }
        ],
        "responses": {
          "200": {
            "description": "OK",
            "content": {
              "text/plain": {
                "schema": {
                  "type": "array",
                  "items": {
                    "$ref": "#/components/schemas/OvniData"
                  }
                }
              },
              "application/json": {
                "schema": {
                  "type": "array",
                  "items": {
                    "$ref": "#/components/schemas/OvniData"
                  }
                }
              },
              "text/json": {
                "schema": {
                  "type": "array",
                  "items": {
                    "$ref": "#/components/schemas/OvniData"
                  }
                }
              }
            }
          }
        }
      }
    },
    "/api/OvniData/range": {
      "get": {
        "tags": [
          "OvniData"
        ],
        "parameters": [
          {
            "name": "alturaMin",
            "in": "query",
            "schema": {
              "type": "number",
              "format": "double"
            }
          },
          {
            "name": "alturaMax",
            "in": "query",
            "schema": {
              "type": "number",
              "format": "double"
            }
          }
        ],
        "responses": {
          "200": {
            "description": "OK",
            "content": {
              "text/plain": {
                "schema": {
                  "type": "array",
                  "items": {
                    "$ref": "#/components/schemas/OvniData"
                  }
                }
              },
              "application/json": {
                "schema": {
                  "type": "array",
                  "items": {
                    "$ref": "#/components/schemas/OvniData"
                  }
                }
              },
              "text/json": {
                "schema": {
                  "type": "array",
                  "items": {
                    "$ref": "#/components/schemas/OvniData"
                  }
                }
              }
            }
          }
        }
      }
    }
  },
  "components": {
    "schemas": {
      "OvniData": {
        "type": "object",
        "properties": {
          "id": {
            "type": "string",
            "nullable": true
          },
          "hexId": {
            "type": "string",
            "nullable": true
          },
          "squawk": {
            "type": "integer",
            "format": "int32"
          },
          "flight": {
            "type": "string",
            "nullable": true
          },
          "lat": {
            "type": "number",
            "format": "double"
          },
          "lon": {
            "type": "number",
            "format": "double"
          },
          "altitude": {
            "type": "number",
            "format": "double"
          },
          "vertRate": {
            "type": "integer",
            "format": "int32"
          },
          "track": {
            "type": "number",
            "format": "double"
          },
          "speed": {
            "type": "integer",
            "format": "int32"
          },
          "origem": {
            "type": "string",
            "nullable": true
          },
          "destino": {
            "type": "string",
            "nullable": true
          },
          "data": {
            "type": "string",
            "format": "date-time"
          },
          "companhiaAerea": {
            "type": "string",
            "nullable": true
          }
        },
        "additionalProperties": false
      }
    }
  }
}